pluto_client/__init__.py
pluto_client/bucket.py
pluto_client/clients/__init__.py
pluto_client/clients/aws/__init__.py
pluto_client/clients/aws/bucket_s3.py
pluto_client/clients/aws/function_lambda.py
pluto_client/clients/aws/kvstore_dynamodb.py
pluto_client/clients/aws/queue_sns.py
pluto_client/clients/aws/sagemaker.py
pluto_client/clients/aws/secret_secretsmgr.py
pluto_client/clients/aws/utils.py
pluto_client/clients/errors.py
pluto_client/clients/shared/__init__.py
pluto_client/clients/shared/router.py
pluto_client/clients/shared/website.py
pluto_client/function.py
pluto_client/kvstore.py
pluto_client/queue.py
pluto_client/reactapp.py
pluto_client/router.py
pluto_client/sagemaker.py
pluto_client/schedule.py
pluto_client/secret.py
pluto_client/tester.py
pluto_client/utils.py
pluto_client/website.py
pluto_client-0.0.20.dist-info/LICENSE
pluto_client-0.0.20.dist-info/METADATA
pluto_client-0.0.20.dist-info/WHEEL
pluto_client-0.0.20.dist-info/RECORD
