Metadata-Version: 2.1
Name: pluto-client
Version: 0.0.20
Summary: The Client Library for Pluto Programming Language.
License: Apache-2.0
Author: Jade Zheng
Author-email: zheng.shoujian@outlook.com
Requires-Python: >=3.10,<4.0
Classifier: Development Status :: 1 - Planning
Classifier: Environment :: Console
Classifier: Intended Audience :: Developers
Classifier: License :: OSI Approved :: Apache Software License
Classifier: Natural Language :: English
Classifier: Programming Language :: Python :: 3
Classifier: Programming Language :: Python :: 3.10
Classifier: Programming Language :: Python :: 3.11
Classifier: Programming Language :: Python :: 3.12
Classifier: Topic :: Software Development
Requires-Dist: pluto-base (>=0.0.7,<0.0.8)
Project-URL: Homepage, https://github.com/pluto-lang/pluto
Project-URL: Issues, https://github.com/pluto-lang/pluto/issues
